setup.py
test_distributions_777/Binomialdistribution.py
test_distributions_777/Gaussiandistribution.py
test_distributions_777/Generaldistribution.py
test_distributions_777/__init__.py
test_distributions_777.egg-info/PKG-INFO
test_distributions_777.egg-info/SOURCES.txt
test_distributions_777.egg-info/dependency_links.txt
test_distributions_777.egg-info/not-zip-safe
test_distributions_777.egg-info/top_level.txt